devdocs2zim/__about__.py
devdocs2zim/__init__.py
devdocs2zim/client.py
devdocs2zim/constants.py
devdocs2zim/entrypoint.py
devdocs2zim/generator.py
devdocs2zim/templates/licenses.txt
devdocs2zim/templates/page.html
devdocs2zim/third_party/devdocs/COPYRIGHT
devdocs2zim/third_party/devdocs/LICENSE
devdocs2zim/third_party/devdocs/README.md
devdocs2zim/third_party/devdocs/devdocs_48.png
devdocs2zim-0.2.0.dist-info/METADATA
devdocs2zim-0.2.0.dist-info/WHEEL
devdocs2zim-0.2.0.dist-info/entry_points.txt
devdocs2zim-0.2.0.dist-info/licenses/LICENSE
devdocs2zim-0.2.0.dist-info/RECORD
