Metadata-Version: 2.1
Name: devdocs2zim
Version: 0.2.0
Summary: Make ZIM files from DevDocs.io
Project-URL: Donate, https://www.kiwix.org/en/support-us/
Project-URL: Homepage, https://github.com/openzim/devdocs
Author-email: openZIM <dev@openzim.org>
License: GPL-3.0-or-later
License-File: LICENSE
Keywords: devdocs,offline,openzim,zim
Classifier: License :: OSI Approved :: GNU General Public License v3 or later (GPLv3+)
Classifier: Programming Language :: Python :: 3
Classifier: Programming Language :: Python :: 3.12
Requires-Python: <3.13,>=3.12
Requires-Dist: beautifulsoup4==4.12.3
Requires-Dist: jinja2==3.1.4
Requires-Dist: pydantic==2.9.2
Requires-Dist: requests==2.32.3
Requires-Dist: zimscraperlib==4.0.0
Provides-Extra: check
Requires-Dist: pyright==1.1.388; extra == 'check'
Provides-Extra: dev
Requires-Dist: debugpy==1.8.8; extra == 'dev'
Requires-Dist: devdocs2zim[check]; extra == 'dev'
Requires-Dist: devdocs2zim[lint]; extra == 'dev'
Requires-Dist: devdocs2zim[scripts]; extra == 'dev'
Requires-Dist: devdocs2zim[test]; extra == 'dev'
Requires-Dist: pre-commit==4.0.1; extra == 'dev'
Provides-Extra: lint
Requires-Dist: black==24.10.0; extra == 'lint'
Requires-Dist: ruff==0.7.3; extra == 'lint'
Provides-Extra: scripts
Requires-Dist: invoke==2.2.0; extra == 'scripts'
Provides-Extra: test
Requires-Dist: coverage==7.6.4; extra == 'test'
Requires-Dist: pytest==8.3.3; extra == 'test'
